nautilusdb/__init__.py
nautilusdb/client/__init__.py
nautilusdb/client/admin_management.py
nautilusdb/client/collection_management.py
nautilusdb/client_models/__init__.py
nautilusdb/client_models/chat.py
nautilusdb/client_models/collection.py
nautilusdb/client_models/doc.py
nautilusdb/server_models/__init__.py
nautilusdb/server_models/admin_api.py
nautilusdb/server_models/collection_api.py
nautilusdb/server_models/doc_api.py
nautilusdb/tests/api_surface_test.py
nautilusdb/tests/data/española.txt
nautilusdb/tests/data/française.txt
nautilusdb/tests/data/text_file.txt
nautilusdb/tests/data/中文.txt
nautilusdb/tests/smoke_test.py
nautilusdb/utils/__init__.py
nautilusdb/utils/ask.py
nautilusdb/utils/config.py
nautilusdb/utils/exceptions.py
nautilusdb/utils/file_upload.py
nautilusdb_client-0.8.0.dist-info/LICENSE
nautilusdb_client-0.8.0.dist-info/METADATA
nautilusdb_client-0.8.0.dist-info/WHEEL
nautilusdb_client-0.8.0.dist-info/RECORD
