Metadata-Version: 2.1
Name: nautilusdb-client
Version: 0.8.0
Summary: Python client for NautilusDB
Author: NautilusDB
Author-email: contact@nautilusdb.com
Requires-Python: >=3.10,<4.0
Classifier: Programming Language :: Python :: 3
Classifier: Programming Language :: Python :: 3.10
Classifier: Programming Language :: Python :: 3.11
Classifier: Programming Language :: Python :: 3.12
Requires-Dist: pydantic (>=2.4.2,<3.0.0)
Requires-Dist: requests (>=2.31.0,<3.0.0)
